mechcite/__init__.py
mechcite/bibliography.py
mechcite/citation.py
mechcite-0.2.4.dist-info/AUTHORS.rst
mechcite-0.2.4.dist-info/LICENSE
mechcite-0.2.4.dist-info/METADATA
mechcite-0.2.4.dist-info/WHEEL
mechcite-0.2.4.dist-info/top_level.txt
mechcite-0.2.4.dist-info/RECORD
