Metadata-Version: 2.1
Name: mechcite
Version: 0.2.4
Summary: Python package for decorating classes and functions with a citation and generating a bibliography when those are used
Home-page: https://github.com/mecheng/mechcite
Author: Jelle Spijker
Author-email: spijker.jelle@gmail.com
License: MIT license
Keywords: mechcite
Platform: UNKNOWN
Classifier: Development Status :: 2 - Pre-Alpha
Classifier: Intended Audience :: Developers
Classifier: License :: OSI Approved :: MIT License
Classifier: Natural Language :: English
Classifier: Programming Language :: Python :: 3
Classifier: Programming Language :: Python :: 3.4
Classifier: Programming Language :: Python :: 3.5
Classifier: Programming Language :: Python :: 3.6
Classifier: Programming Language :: Python :: 3.7
Requires-Dist: pytablewriter
Requires-Dist: pybtex
Requires-Dist: dominate
